Metadata-Version: 2.4
Name: django-models
Version: 1.0
Summary: Library with several useful Models for Django to help you make your Models smart or with less code
Home-page: https://github.com/rhenter/django-models
Author: Rafael Henter
Author-email: rafael@henter.com.br
License: MIT
Keywords: models tools django signal
Classifier: Development Status :: 5 - Production/Stable
Classifier: Framework :: Django
Classifier: Intended Audience :: Developers
Classifier: License :: OSI Approved :: MIT License
Classifier: Programming Language :: Python :: 3
Classifier: Programming Language :: Python :: 3.8
Classifier: Programming Language :: Python :: 3.9
Classifier: Programming Language :: Python :: 3.10
Classifier: Programming Language :: Python :: 3.11
Classifier: Programming Language :: Python :: 3.12
Classifier: Topic :: Software Development :: Libraries
Classifier: Topic :: Software Development :: Libraries :: Python Modules
Classifier: Typing :: Typed
License-File: LICENSE
Requires-Dist: cached_property>=1.3.0
Requires-Dist: django>=5.0
Requires-Dist: djangorestframework>=3.7
Requires-Dist: unipath
Dynamic: author
Dynamic: author-email
Dynamic: classifier
Dynamic: description
Dynamic: home-page
Dynamic: keywords
Dynamic: license
Dynamic: license-file
Dynamic: requires-dist
Dynamic: summary
